# Задача 1
Изучите возможности просмотра байткода ВМ CPython.

```
import dis

def foo(x):
    while x:
        x -= 1
    return x + 1

print(dis.dis(foo))
```
Опишите по шагам, что делает каждая из следующих команд (приведите эквивалентное выражение на Python):

11 0 LOAD_FAST 0 (x) 2 LOAD_CONST 1 (10) 4 BINARY_MULTIPLY 6 LOAD_CONST 2 (42) 8 BINARY_ADD 10 RETURN_VALUE

## Решение
LOAD_FAST 0 (x) - Загружает значение переменной x 
```
x
```
LOAD_CONST 1 (10) - Загружает константу 10
```
10
```
BINARY_MULTIPLY - Умножает два значения в стеке (значение переменной x и константу 10)
```
x * 10
```
LOAD_CONST 2 (42) - Загружает константу 42
```
42
```
BINARY_ADD - Складывает два значения в стеке (результат умножения x * 10 и константу 42)
```
(x * 10) + 42
```

RETURN_VALUE - Возвращает значение, которое находится в стеке (результат выражения (x * 10) + 42)
```
return (x * 10) + 42
```

# Задача 2
Что делает следующий байткод (опишите шаги его работы)? Это известная функция, назовите ее.
```
  5           0 LOAD_CONST               1 (1)
              2 STORE_FAST               1 (r)

  6     >>    4 LOAD_FAST                0 (n)
              6 LOAD_CONST               1 (1)
              8 COMPARE_OP               4 (>)
             10 POP_JUMP_IF_FALSE       30

  7          12 LOAD_FAST                1 (r)
             14 LOAD_FAST                0 (n)
             16 INPLACE_MULTIPLY
             18 STORE_FAST               1 (r)

  8          20 LOAD_FAST                0 (n)
             22 LOAD_CONST               1 (1)
             24 INPLACE_SUBTRACT
             26 STORE_FAST               0 (n)
             28 JUMP_ABSOLUTE            4

  9     >>   30 LOAD_FAST                1 (r)
             32 RETURN_VALUE
```

## Решение
Функция вычиления факотриала числа.

  1. Инициализация переменной r:
     
LOAD_CONST 1 (1) — загружается константа 1.

STORE_FAST 1 (r) — значение 1 сохраняется в переменной r.

  2. Проверка условия цикла (пока n > 1):

LOAD_FAST 0 (n) — загружается значение переменной n.

LOAD_CONST 1 (1) — загружается константа 1.

COMPARE_OP 4 (>) — выполняется проверка: n > 1.

POP_JUMP_IF_FALSE 30 — если n не больше 1, переход к строке 30 (выход из цикла).

  3.Умножение результата на n:
  
LOAD_FAST 1 (r) — загружается текущее значение переменной r.

LOAD_FAST 0 (n) — загружается значение n.

INPLACE_MULTIPLY — выполняется операция умножения: r = r * n.

STORE_FAST 1 (r) — результат сохраняется обратно в переменную r.

  4.Уменьшение n на 1:
  
LOAD_FAST 0 (n) — загружается значение n.

LOAD_CONST 1 (1) — загружается константа 1.

INPLACE_SUBTRACT — выполняется операция вычитания: n = n - 1.

STORE_FAST 0 (n) — результат сохраняется обратно в n.

JUMP_ABSOLUTE 4 — переход к строке 4 для повторной проверки условия.

  5. Возврат результата (выход из цикла):

LOAD_FAST 1 (r) — загружается результат.

RETURN_VALUE — возвращается значение переменной r, которое является факториалом числа n.
